aiovoip/__init__.py
aiovoip/application.py
aiovoip/auth.py
aiovoip/contact.py
aiovoip/dialog.py
aiovoip/dialplan.py
aiovoip/exceptions.py
aiovoip/message.py
aiovoip/param.py
aiovoip/peers.py
aiovoip/protocol.py
aiovoip/pytest_plugin.py
aiovoip/transaction.py
aiovoip/uri.py
aiovoip/utils.py
aiovoip/via.py
aiovoip-0.2.3.dist-info/licenses/LICENSE
aiovoip-0.2.3.dist-info/METADATA
aiovoip-0.2.3.dist-info/WHEEL
aiovoip-0.2.3.dist-info/top_level.txt
aiovoip-0.2.3.dist-info/RECORD
