Metadata-Version: 2.4
Name: aiovoip
Version: 0.2.3
Summary: AioVoIP - Asynchronous VoIP library for Python
Author-email: Vardan Aloyan <valoyan2@gmail.com>
Project-URL: Homepage, https://github.com/py-craft/aiovoip
Project-URL: Repository, https://github.com/py-craft/aiovoip
Project-URL: Issues, https://github.com/py-craft/aiovoip/issues
Classifier: Intended Audience :: Information Technology
Classifier: Intended Audience :: Telecommunications Industry
Classifier: Operating System :: OS Independent
Classifier: Programming Language :: Python :: 3
Classifier: Programming Language :: Python
Classifier: Topic :: Internet
Classifier: Topic :: Software Development :: Libraries :: Application Frameworks
Classifier: Topic :: Software Development :: Libraries :: Python Modules
Classifier: Topic :: Software Development :: Libraries
Classifier: Topic :: Software Development
Classifier: Intended Audience :: Developers
Classifier: Programming Language :: Python :: 3 :: Only
Classifier: Programming Language :: Python :: 3.11
Classifier: Programming Language :: Python :: 3.12
Classifier: Programming Language :: Python :: 3.13
Requires-Python: >=3.11
License-File: LICENSE
Requires-Dist: multidict>=2.0
Requires-Dist: pyquery
Requires-Dist: aiodns
Requires-Dist: websockets
Requires-Dist: async-timeout
Dynamic: license-file
